{"bookId":21537,"pg":15318,"printedPage":41,"volume":"29","bookName":"مجموع فتاوى ومقالات متنوعة - ابن باز","authorName":"ابن باز","text":"٢٤ - بيان أن شعر العارضين من اللحية\nس: ما حكم حلق اللحية وحكم حلق العارضين وترك اللحية والشارب؟\nج: حلق اللحية لا يجوز لقول النبي ﷺ في الحديث الصحيح: «قصوا الشوارب وأعفوا اللحى، خالفوا المشركين (١)» أخرجه مسلم في صحيحه.\nواللحية هي ما نبت على الخدين والذقن كما أوضح ذلك صاحب القاموس، فالواجب ترك الشعر النابت على الخدين والذقن وعدم حلقه أو قصه، أصلح الله حال المسلمين جميعا.\n_________\n(١) أخرجه الإمام أحمد في باقي مسند المكثرين، مسند أبي هريرة برقم ٧٠٩٢.","url":"https://shamela.ws/book/21537/15318"}